Dark_Angel/__init__.py
Dark_Angel/project.py
Dark_Angel-1.3.dist-info/METADATA
Dark_Angel-1.3.dist-info/WHEEL
Dark_Angel-1.3.dist-info/top_level.txt
Dark_Angel-1.3.dist-info/RECORD
