Metadata-Version: 2.1
Name: Dark-Angel
Version: 1.3
Summary: prints ❤️Dark Angel❤️
Author: Dark Angel
